justhtml/__init__.py
justhtml/__main__.py
justhtml/constants.py
justhtml/context.py
justhtml/encoding.py
justhtml/entities.py
justhtml/errors.py
justhtml/linkify.py
justhtml/node.py
justhtml/parser.py
justhtml/py.typed
justhtml/sanitize.py
justhtml/selector.py
justhtml/serialize.py
justhtml/stream.py
justhtml/tokenizer.py
justhtml/tokens.py
justhtml/transforms.py
justhtml/treebuilder.py
justhtml/treebuilder_modes.py
justhtml/treebuilder_utils.py
justhtml-1.4.0.dist-info/METADATA
justhtml-1.4.0.dist-info/WHEEL
justhtml-1.4.0.dist-info/entry_points.txt
justhtml-1.4.0.dist-info/licenses/LICENSE
justhtml-1.4.0.dist-info/RECORD
