Metadata-Version: 2.4
Name: justhtml
Version: 1.4.0
Summary: A pure Python HTML5 parser that just works.
Project-URL: Homepage, https://github.com/emilstenstrom/justhtml
Project-URL: Issues, https://github.com/emilstenstrom/justhtml/issues
Author-email: Emil Stenström <emil@emilstenstrom.se>
License: MIT License
License-File: LICENSE
Classifier: License :: OSI Approved :: MIT License
Classifier: Operating System :: OS Independent
Classifier: Programming Language :: Python :: 3
Requires-Python: >=3.10
Provides-Extra: benchmark
Requires-Dist: beautifulsoup4; extra == 'benchmark'
Requires-Dist: html5-parser; extra == 'benchmark'
Requires-Dist: html5lib; extra == 'benchmark'
Requires-Dist: lxml; extra == 'benchmark'
Requires-Dist: psutil; extra == 'benchmark'
Requires-Dist: selectolax; extra == 'benchmark'
Requires-Dist: zstandard; extra == 'benchmark'
Provides-Extra: dev
Requires-Dist: build; extra == 'dev'
Requires-Dist: coverage; extra == 'dev'
Requires-Dist: mypy>=1.0; (platform_python_implementation != 'PyPy') and extra == 'dev'
Requires-Dist: pre-commit; extra == 'dev'
Requires-Dist: ruff==0.14.7; extra == 'dev'
Requires-Dist: twine; extra == 'dev'
